foxglove_schemas_flatbuffer/ArrowPrimitive.bfbs
foxglove_schemas_flatbuffer/ArrowPrimitive.py
foxglove_schemas_flatbuffer/ByteVector.bfbs
foxglove_schemas_flatbuffer/ByteVector.py
foxglove_schemas_flatbuffer/CameraCalibration.bfbs
foxglove_schemas_flatbuffer/CameraCalibration.py
foxglove_schemas_flatbuffer/CircleAnnotation.bfbs
foxglove_schemas_flatbuffer/CircleAnnotation.py
foxglove_schemas_flatbuffer/Color.bfbs
foxglove_schemas_flatbuffer/Color.py
foxglove_schemas_flatbuffer/CompressedImage.bfbs
foxglove_schemas_flatbuffer/CompressedImage.py
foxglove_schemas_flatbuffer/CompressedVideo.bfbs
foxglove_schemas_flatbuffer/CompressedVideo.py
foxglove_schemas_flatbuffer/CubePrimitive.bfbs
foxglove_schemas_flatbuffer/CubePrimitive.py
foxglove_schemas_flatbuffer/CylinderPrimitive.bfbs
foxglove_schemas_flatbuffer/CylinderPrimitive.py
foxglove_schemas_flatbuffer/Duration.bfbs
foxglove_schemas_flatbuffer/Duration.py
foxglove_schemas_flatbuffer/FrameTransform.bfbs
foxglove_schemas_flatbuffer/FrameTransform.py
foxglove_schemas_flatbuffer/FrameTransforms.bfbs
foxglove_schemas_flatbuffer/FrameTransforms.py
foxglove_schemas_flatbuffer/GeoJSON.bfbs
foxglove_schemas_flatbuffer/GeoJSON.py
foxglove_schemas_flatbuffer/Grid.bfbs
foxglove_schemas_flatbuffer/Grid.py
foxglove_schemas_flatbuffer/ImageAnnotations.bfbs
foxglove_schemas_flatbuffer/ImageAnnotations.py
foxglove_schemas_flatbuffer/KeyValuePair.bfbs
foxglove_schemas_flatbuffer/KeyValuePair.py
foxglove_schemas_flatbuffer/LaserScan.bfbs
foxglove_schemas_flatbuffer/LaserScan.py
foxglove_schemas_flatbuffer/LinePrimitive.bfbs
foxglove_schemas_flatbuffer/LinePrimitive.py
foxglove_schemas_flatbuffer/LineType.py
foxglove_schemas_flatbuffer/LocationFix.bfbs
foxglove_schemas_flatbuffer/LocationFix.py
foxglove_schemas_flatbuffer/Log.bfbs
foxglove_schemas_flatbuffer/Log.py
foxglove_schemas_flatbuffer/LogLevel.py
foxglove_schemas_flatbuffer/ModelPrimitive.bfbs
foxglove_schemas_flatbuffer/ModelPrimitive.py
foxglove_schemas_flatbuffer-0.3.0.dist-info/METADATA
foxglove_schemas_flatbuffer-0.3.0.dist-info/WHEEL
foxglove_schemas_flatbuffer-0.3.0.dist-info/RECORD
