Metadata-Version: 2.3
Name: foxglove-schemas-flatbuffer
Version: 0.3.0
Summary: Precompiled flatbuffer schemas for Foxglove
License: MIT
Author: Foxglove
Author-email: support@foxglove.dev
Requires-Python: >=3.9
Classifier: License :: OSI Approved :: MIT License
Classifier: Programming Language :: Python :: 3
Classifier: Programming Language :: Python :: 3.9
Classifier: Programming Language :: Python :: 3.10
Classifier: Programming Language :: Python :: 3.11
Classifier: Programming Language :: Python :: 3.12
Classifier: Programming Language :: Python :: 3.13
Requires-Dist: flatbuffers (>=23.0)
Project-URL: Documentation, https://docs.foxglove.dev/
Project-URL: Repository, https://github.com/foxglove/schemas
